README.md
setup.cfg
setup.py
example/__init__.py
example/main.py
tests/__init__.py
tests/entries.py
tests/main_test.py
xchain/__init__.py
xchain/xchain.py
xchain.egg-info/PKG-INFO
xchain.egg-info/SOURCES.txt
xchain.egg-info/dependency_links.txt
xchain.egg-info/requires.txt
xchain.egg-info/top_level.txt
xchain/encryption/__init__.py
xchain/encryption/crypto.py
xchain/encryption/encrypt.py
xchain/encryption/keymaker.py
xchain/utils/__init__.py
xchain/utils/utils.py