Metadata-Version: 2.1
Name: xchain
Version: 0.0.1
Summary: A generic blockchain library
Home-page: https://github.com/kobibarhanin/xchain
Author: kobibarhanin
Author-email: 
License: UNKNOWN
Platform: UNKNOWN
Classifier: Programming Language :: Python :: 3
Classifier: License :: OSI Approved :: MIT License
Classifier: Operating System :: OS Independent
Requires-Python: >=3.7
